django_rest_mfa/__init__.py
django_rest_mfa/admin.py
django_rest_mfa/apps.py
django_rest_mfa/constants.py
django_rest_mfa/fido2.py
django_rest_mfa/fields.py
django_rest_mfa/helpers.py
django_rest_mfa/mfa_admin/__init__.py
django_rest_mfa/mfa_admin/apps.py
django_rest_mfa/mfa_admin/static/django_rest_mfa/cbor.js
django_rest_mfa/mfa_admin/static/django_rest_mfa/fido2_add.js
django_rest_mfa/mfa_admin/static/django_rest_mfa/otp_add.js
django_rest_mfa/mfa_admin/static/django_rest_mfa/qrcode.js
django_rest_mfa/mfa_admin/static/django_rest_mfa/second_factor.js
django_rest_mfa/mfa_admin/static/django_rest_mfa/utils.js
django_rest_mfa/mfa_admin/templates/admin/base_site.html
django_rest_mfa/mfa_admin/templates/django_rest_mfa/fido2_add.html
django_rest_mfa/mfa_admin/templates/django_rest_mfa/login.html
django_rest_mfa/mfa_admin/templates/django_rest_mfa/otp_add.html
django_rest_mfa/mfa_admin/templates/django_rest_mfa/second_factor.html
django_rest_mfa/mfa_admin/templates/django_rest_mfa/userkey_confirm_delete.html
django_rest_mfa/mfa_admin/templates/django_rest_mfa/userkey_list.html
django_rest_mfa/mfa_admin/urls.py
django_rest_mfa/mfa_admin/views.py
django_rest_mfa/migrations/0001_initial.py
django_rest_mfa/migrations/0002_alter_userkey_key_type.py
django_rest_mfa/migrations/__init__.py
django_rest_mfa/models.py
django_rest_mfa/parsers.py
django_rest_mfa/renderers.py
django_rest_mfa/rest_auth_helpers/serializers.py
django_rest_mfa/rest_auth_helpers/utils.py
django_rest_mfa/rest_auth_helpers/views.py
django_rest_mfa/serializers.py
django_rest_mfa/settings.py
django_rest_mfa/tests.py
django_rest_mfa/totp.py
django_rest_mfa/trusted_device.py
django_rest_mfa/urls.py
django_rest_mfa/views.py
django_rest_mfa-1.2.2.dist-info/LICENSE
django_rest_mfa-1.2.2.dist-info/METADATA
django_rest_mfa-1.2.2.dist-info/WHEEL
django_rest_mfa-1.2.2.dist-info/RECORD
